LICENSE
README.md
setup.py
multivaluedbtree/__init__.py
multivaluedbtree/btree.py
multivaluedbtree.egg-info/PKG-INFO
multivaluedbtree.egg-info/SOURCES.txt
multivaluedbtree.egg-info/dependency_links.txt
multivaluedbtree.egg-info/requires.txt
multivaluedbtree.egg-info/top_level.txt
test/test_btree.py