Metadata-Version: 2.1
Name: multivaluedbtree
Version: 0.0.1
Summary: A multivalued BTree.
Home-page: https://github.com/jmgomezsoriano/multivaluedbtree
Author: José Manuel Gómez Soriano
Author-email: jmgomez.soriano@gmail.com
License: LGPL2
Platform: UNKNOWN
Classifier: Programming Language :: Python :: 3
Classifier: License :: OSI Approved :: MIT License
Classifier: Operating System :: OS Independent
Requires-Python: >=3.7
License-File: LICENSE
